src/__init__.py
src/main.py
testforallen-1.0.dist-info/METADATA
testforallen-1.0.dist-info/WHEEL
testforallen-1.0.dist-info/top_level.txt
testforallen-1.0.dist-info/RECORD
